Metadata-Version: 2.1
Name: TopEmoji
Version: 0.1.2
Summary: 🔎 the most similar 😀s.
Home-page: https://github.com/chuanconggao/TopEmoji
Author: Chuancong Gao
Author-email: chuancong@gmail.com
License: MIT
Download-URL: https://github.com/chuanconggao/TopEmoji/tarball/0.1.2
Keywords: similarity-search,string-search,emoji
Platform: UNKNOWN
Classifier: Operating System :: OS Independent
Classifier: Programming Language :: Python
Classifier: Programming Language :: Python :: 3
Requires-Python: >= 3
